NR_Python/__init__.py
NR_Python-0.0.1.dist-info/METADATA
NR_Python-0.0.1.dist-info/WHEEL
NR_Python-0.0.1.dist-info/top_level.txt
NR_Python-0.0.1.dist-info/RECORD
